CHANGES.txt
LICENSE.txt
MANIFEST.in
README.rst
bottle_servefiles.py
setup.py
bottle_servefiles.egg-info/PKG-INFO
bottle_servefiles.egg-info/SOURCES.txt
bottle_servefiles.egg-info/dependency_links.txt
bottle_servefiles.egg-info/not-zip-safe
bottle_servefiles.egg-info/top_level.txt