Metadata-Version: 1.0
Name: bottle-servefiles
Version: 0.1.1dev
Summary: A reusable app that serves static files for bottle apps
Home-page: https://bitbucket.org/rudylattae/bottle-servefiles
Author: Rudy Lattae
Author-email: rudylattae@gmail.com
License: Simplified BSD
Keywords: bottle,bottle.py,static,file,files,web,app
Platform: UNKNOWN
Classifier: Development Status :: 2 - Pre-Alpha
Classifier: Environment :: Web Environment
Classifier: Intended Audience :: Developers
Classifier: License :: OSI Approved :: BSD License
Classifier: Operating System :: Microsoft :: Windows
Classifier: Programming Language :: Python
Classifier: Programming Language :: Python :: 2.7
